{
  "id": 370,
  "title": "수박을 꿀에 찍어 먹는 하회 류 교장네 장원풍경",
  "date": "14.06.22",
  "text": "오랫만에 하회, 광덕에 사는\n\n류 길하 교장의 경성재 임원농장을 방문하였다.\n\n \n\n몇차례 안부 전화를 받고\n\n얼굴 잊어버릴까 걱정이라는 농을 나눈 끝에\n\n마침 절친인 하 재인 국장을 만나고 싶다고 했었는데\n\n바로 그 사람과 점심을 먹고난 뒤라\n\n생각난김에 방문하자는 갑짝스런 행보가 된 것이다.\n\n \n\n또 서울사는 구천아제가 또 류 교장소식이냐고\n\n핀잔아닌 투정이 있을것이나 사실 동기친구들이\n\n대부분 두문불출이라 소식을 전할 기회를 잡지못하여\n\n자주 소식주고 받는 류 교장 소식이 자주 등장하는건 할수 없다.\n\n \n\n요즈음은 신 경북도 청사 신축현장에 감리사로 일하는\n\n류 교장 아드님이 내가 몸담고 있는 안동권 발전연구소에 나와\n\n오히려 더 자주 만나는 사이가 되었다.\n\n \n\n넉넉한 웃음과 두터운 손으로 맞잡은 반가운 인사를 나누자 마자\n\n뒷편 산속으로 새로 깨끗이 포장한 새길로 우리를 이끈다.\n\n \n\n안내견 개는 아주 익숙하게 우리들 앞에서 느릿하게 걸어가고\n\n칠면조 몇마리가 날개를 한껏 펼쳐들고 위협적인 씩씩거림을하고\n\n거위 한쌍이 마치 마주 싸우듯 달려들다가 쫒겨가고\n\n토종닭인지 여러마리 오색이 섞여 화려한 깃털을 한놈들이\n\n한가하게 화들짝 꽃잎을 자랑하며 활짝핀 접시꽃 사이로 \n\n갖 깬 병아리들을 몰고 모이를 쫒고 있다.\n\n \n\n그동안 정성을 얼마나 들였는지\n\n얼마전 방문길에 돌아봤던 산길이 말끔히 다듬어져 \n\n몰라볼만큼 깜끔하게 정리가 끝나있다.\n\n \n\n하여튼 크레믈린 곰 같은 인사인지라\n\n일하는것도 끈질기고 부지런하다.\n\n사모님이 \" 내가 못살겠심더 \" 하시는걸 보면\n\n일에 몸서리를 치고 두손을 모두다 든 모습이다.\n\n \n\n내가 대강 스켓치해본 상황으론\n\n류 교장 임원풍경을 온전히 전할길이 없어 유감이다.\n\n \n\n우리는 한바퀴 휘 ~ 둘러보고 난뒤\n\n자그만 연못가에 있는 정자 난간에 앉아 숨을 돌리니\n\n맛있는 매실차와 수박, 그리고 이집 특기인\n\n꿀 한잔씩을 내어온다.\n\n \n\n어이, 이 관장,  자네 수박을 꿀에 찍어 먹어 봤나 ?\n\n한번 찍어 먹어보게 !  맛있을 걸세.\n\n세상에 !  수박도 요즘 달디단데\n\n그걸 또 꿀에 찍어 먹는단 말이지 하고\n\n수박을 꿀에 발라 먹어보는 동행한 임 대사가\n\n아, 정말 향도 좋고,  맛도 훨씬 더 있니더 ! 한다.\n\n \n\n정말이다. \n\n 향이 우선 더 찐~하고 맛도 훨씬 좋긴 좋다.\n\n허긴 꿀이 흔한 집이니 무슨 짓인들 못할까 ?\n\n \n\n어쨌든 하회 류 교장은 \n\n애써서 농사지어서 그저 남에게 나누어주는 재미로 사나보다.\n\n \n\n텃밭에 쌈 채소가 지천이다.\n\n동직원들이 모여와 솎아내었다는데도\n\n이곳저곳 채소를 감당하지 못하는듯 하다.\n\n쌈밥집 어디 단골두고 보내도 남고 남을듯 하다. \n\n \n\n서울 사는 친구들에게\n\n마음껏 가져가라고 하고싶다만\n\n거리가 멀고 먼지라...\n\n \n\n마당엔 솎아낸 배추 상추가 시레기가 다되어\n\n퇴비장으로 실려가고 있는데...\n\n \n\n오늘도 우린 하회에 나와 앉아\n\n유유자적 산속에 뭍혀\n\n수박에 꿀발라 먹으며\n\n싱거운 농을 나누고 있다.\n\n \n\n그저 더도말고 덜도말고\n\n오늘 같이 ,  이같이 살면 좋으련만...",
  "images": [
    "https://m1.daumcdn.net/cfile268/image/212CB24953A67DD92D79BB",
    "https://m1.daumcdn.net/cfile244/image/2229B84953A67DDA32EF33",
    "https://m1.daumcdn.net/cfile265/image/2629D14953A67DDC32F892",
    "https://m1.daumcdn.net/cfile252/image/2731C74953A67DDD259424",
    "https://m1.daumcdn.net/cfile271/image/2105A43453A6751C22D2C6",
    "https://m1.daumcdn.net/cfile279/image/2413233453A6751E0F0A5F",
    "https://m1.daumcdn.net/cfile300/image/2210023453A6752013A563",
    "https://m1.daumcdn.net/cfile285/image/2319483453A67524032199",
    "https://m1.daumcdn.net/cfile300/image/2403C13453A6752824DF45",
    "https://m1.daumcdn.net/cfile275/image/217B823453A6752A2FEB19",
    "https://m1.daumcdn.net/cfile295/image/240CFA3453A6752C18A2CE",
    "https://m1.daumcdn.net/cfile247/image/2704083453A6752E250CF4",
    "https://m1.daumcdn.net/cfile279/image/2406483453A6753022A33E",
    "https://m1.daumcdn.net/cfile283/image/260F003453A675331525A7",
    "https://m1.daumcdn.net/cfile255/image/2516B43453A6753708FD5B",
    "https://m1.daumcdn.net/cfile263/image/2518C93453A6753905E170",
    "https://m1.daumcdn.net/cfile279/image/2215763453A6753B0BF0EF",
    "https://m1.daumcdn.net/cfile273/image/2179C73453A6753C34E30B",
    "https://m1.daumcdn.net/cfile296/image/250DF13753A6753E0C4ACF",
    "https://m1.daumcdn.net/cfile264/image/2609F83753A67540117744",
    "https://m1.daumcdn.net/cfile276/image/2714943753A67542015882",
    "https://m1.daumcdn.net/cfile246/image/257CF83753A67544261BA5"
  ],
  "url": "https://m.cafe.daum.net/123ad/9vTE/370"
}