{
  "id": 455,
  "title": "구담정사 당주, 권 오춘의 기로연",
  "date": "16.07.07",
  "text": "구담정사의 주인인\n\n권 오춘의 기로연을 스켓치하려한다.\n\n \n\n안동의 자랑인\n\n농암 이 현보의 기로연을 아실것이다.\n\n \n\n1519 년 가을, 안동부사로 계실때 \n\n안동에 사는 팔순이 넘는 어른들을\n\n 남여의 성별을 가리지도 않고,\n\n신분, 귀천이나 그밖에 것은 아무것도 보지 않고 \n\n그저 연세 그 하나만 보고\n\n모든 어른들을  관아에 모셔 들이고 \n\n정성된 효심을 보여 주었던,\n\n \n\n몸소 때때옷을 입고  춤까지 추어가면서\n\n 경의 가르침을 파격적으로 실행하였던 바로 그 \n\n화산양로연(花山養老燕) 을 우리는 기로연이라 부른다.\n\n \n\n오늘 우연히 점심자리에서 만난\n\n구담정사의 주인인 권 오춘 선생이\n\n느닷없이 카톡을 보냈으니 한번 보라고 했다.\n\n \n\n열어 보았더니 병산서원의 풍광과 \n\n만대루에서 멋들어진 춤을 추고 있는 본인의 사진이었다.\n\n \n\n원래 동래학춤과 살풀이 양반 춤을 멋들어지게 추어서\n\n많은이들에게 풍류를 느끼게 해 주었던지라\n\n왠 병산서원,  만대루의 풍류인가 물었더니\n\n뜻밖에 이야기를 들려준다.\n\n \n\n많은이에게 춤을 추어 흥을 돋우어 주곤 했지만\n\n정작 96 세의 어머니 한테는 제대로 된 춤을 추어 드리지 못하다가\n\n오늘은 작정하고 비오는 조용한 만대루 누마루에 모친을 모셔놓고\n\n멋들어지게 한판 춤을 추어 즐거움을 드렸다는 것이다.\n\n \n\n와우,   정말 감탄이 저절로 나고\n\n그저 감동으로 숨이 콱 막히는듯한 느낌을 받았다.\n\n \n\n어찌 그런 생각을 했단 말인가  ?\n\n \n\n수많은 사람들에게 흥을 주면서\n\n정작 제일 소중한 모친에게는 보여드리지 못하였던 \n\n그 풍류를 멋들어지게 몸소 보여드렸다니 말이다.\n\n \n\n그래서 생각난 것이 농암선생이 늙은 몸으로도\n\n연세든 많은 안동사람들에게 때때옷 입고 춤추었던 그 풍류가  !\n\n \n\n마침 점심을 대접받고 계시는 모친을보고\n\n참 훌륭한 자제분을 두었다고 덕담을 드리고\n\n그 모습이 너무나 정다와 보이고 보기 좋아서\n\n두 분 사진을 담으려고 하니\n\n풍류를 아는 권 선생은 춤사위 포즈를 지어 보인다.\n\n그 넉넉한 품새와 마음이 너무나 보기 좋다.\n\n \n\n원래 내가 아는 권 선생은\n\n실물경제에 몸담아 꽤 재력을 쌓아 \n\n넉넉한 환경을 살고 계셨는데\n\n안동대학에 봉직하는 동기분\n\n 이 효걸 (동양철학과 교수,문화산업전문대학원장 역임 )교수의 권유로\n\n고전을 읽고 통독하여 전문강의를 하시는 한편\n\n아예 오늘을 사는 선비로서 행신,\n\n예와 악을 그대로 걷고 계시는데,\n\n 선비로서의 몸갖춤을 춤으로 풀어\n\n 풍류남아의 몸가짐을 제대로 보여주고자 한다는데\n\n오늘 얘기 들어보니 안동의 제비원 성주무가의\n\n 제대로된 춤도 익히고 있으니\n\n 한번 보러 양수리로 오라고 하신다.\n\n \n\n대단하고 놀라운 변신이고 \n\n오늘의 우리는 제대로 몸소 실천하는\n\n제모습의 훌륭한 선비를 만나게 된다.\n\n \n\n올해가 가기전에\n\n정말 양수리 풍광좋은 곳에서\n\n그 멋들어진 춤을 보면서\n\n그의 넉넉한 마음과 효심, \n\n그리고 그의 풍류를 만나고 싶다.\n\n \n\n사노라면\n\n생각지 않는\n\n이런 홍재를 만날수도 있는 모양이다.\n\n \n\n멋져요 정말,\n\n \n\n \n\n \n\n \n\n \n\n \n\n紅葉黃花欲暮天 붉은 단풍 누른 국화 해는 장차 저무는데 \n永嘉公館慰高年 안동 고을 관아에서 노인 위로 잔치 하네 \n萊衣舞袖秋風裏 노래자의 춤 소매에 가을바람 일어나고 \n鶴髮童顔壽爵邊 흰머리 소년 얼굴 수연 술잔 올린 다네. \n\n용제총화(慵齊叢話)의 저자 성현(成俔)  축시\n\n \n\n \n\n \n\n \n\n \n\n \n\n \n\n \n\n \n\n \n\n \n\n \n\n \n\n \n\n \n\n \n\n \n\n \n\n \n\n \n\n \n\n \n\n \n\n \n\n \n\n \n\n \n\n \n\n \n\n \n\n \n\n \n\n \n\n \n\n \n\n \n\n \n\n \n\n \n\n \n\n \n\n \n\n \n\n \n\n \n\n \n\n \n\n \n\n \n\n \n\n \n\n \n\n \n\n \n\n요즈음 재현되고 있는 화산양로연,  기로연\n\n권 영세 시장의 때때옷과 춤, 그리고 권주",
  "images": [
    "https://m1.daumcdn.net/cfile290/image/24769D41577DF9FD1681EB",
    "https://m1.daumcdn.net/cfile281/image/27070741577DFA0009F51D",
    "https://m1.daumcdn.net/cfile253/image/2703FA41577DFA210D56B7",
    "https://m1.daumcdn.net/cfile245/image/2408EE41577DFA3D0AE07E",
    "https://m1.daumcdn.net/cfile247/image/23112D41577DFA5E04AABA",
    "https://m1.daumcdn.net/cfile244/image/226C2241577DFA8423A398",
    "https://m1.daumcdn.net/cfile251/image/2503FA41577DFABD134835",
    "https://m1.daumcdn.net/cfile264/image/22255B46577DFAC607A9B3",
    "https://m1.daumcdn.net/cfile253/image/25710B46577DFAC733D426",
    "https://m1.daumcdn.net/cfile288/image/270BE346577DFACA193612",
    "https://m1.daumcdn.net/cfile245/image/25192746577DFACC10D0B9",
    "https://m1.daumcdn.net/cfile299/image/277A443F577DFB4611CB67",
    "https://m1.daumcdn.net/cfile290/image/26075E42577DFBA01BF4CE",
    "https://m1.daumcdn.net/cfile264/image/231A7742577DFBA10968A8",
    "https://m1.daumcdn.net/cfile272/image/216D2642577DFBA32F27FE",
    "https://m1.daumcdn.net/cfile289/image/230BD246577DFACE1ABF26",
    "https://m1.daumcdn.net/cfile269/image/270C7546577DFAD0184FDA",
    "https://m1.daumcdn.net/cfile275/image/241FCA46577DFAD10CED09",
    "https://m1.daumcdn.net/cfile264/image/220AE344577DFAD30EA1D8",
    "https://m1.daumcdn.net/cfile280/image/24595B44577DFAD538F2EB",
    "https://m1.daumcdn.net/cfile259/image/27662644577DFAD72D0665",
    "https://m1.daumcdn.net/cfile263/image/225E0944577DFAD835882A",
    "https://m1.daumcdn.net/cfile246/image/2203A644577DFADB16251F",
    "https://m1.daumcdn.net/cfile270/image/2108CF44577DFADD115439",
    "https://m1.daumcdn.net/cfile271/image/260F8644577DFAE00BE0F7",
    "https://m1.daumcdn.net/cfile256/image/23302740577DFAE21C23DE",
    "https://m1.daumcdn.net/cfile241/image/244C9340577DFAE40AEF73",
    "https://m1.daumcdn.net/cfile243/image/21422240577DFAE71041FE",
    "https://m1.daumcdn.net/cfile277/image/25414240577DFAE812CDFB",
    "https://m1.daumcdn.net/cfile281/image/254A1640577DFAEA0C3119"
  ],
  "url": "https://m.cafe.daum.net/123ad/9vTE/455"
}